ccheck/__init__.py
ccheck/__main__.py
ccheck/ccheck.py
ccheck/config.py
ccheck/container.py
ccheck/domain/__init__.py
ccheck/domain/rule.py
ccheck/domain/validation_error.py
ccheck/domain/exercise/__init__.py
ccheck/domain/exercise/exercise.py
ccheck/domain/exercise/exercise_creator.py
ccheck/domain/exercise/exercise_type.py
ccheck/domain/token/__init__.py
ccheck/domain/token/token.py
ccheck/domain/token/token_type.py
ccheck/exercise/__init__.py
ccheck/exercise/do_while_loop.py
ccheck/exercise/for_loop.py
ccheck/exercise/function_definition.py
ccheck/exercise/if_statement.py
ccheck/exercise/printing_function.py
ccheck/exercise/static_array_declaration.py
ccheck/exercise/switch_statement.py
ccheck/exercise/variable_declaration.py
ccheck/exercise/vla_declaration.py
ccheck/exercise/factories/__init__.py
ccheck/exercise/factories/do_while_loop.py
ccheck/exercise/factories/for_loop.py
ccheck/exercise/factories/function_definition.py
ccheck/exercise/factories/if_statement.py
ccheck/exercise/factories/printing_function.py
ccheck/exercise/factories/static_array_declaration.py
ccheck/exercise/factories/switch_statement.py
ccheck/exercise/factories/variable_declaration.py
ccheck/exercise/factories/vla_declaration.py
ccheck/services/__init__.py
ccheck/services/application.py
ccheck/services/exercise_factory.py
ccheck/services/input.py
ccheck/services/shell.py
ccheck/services/tokenizer.py
ccheck/utils/__init__.py
ccheck/utils/arrays.py
ccheck/utils/validation.py
ccheck_2l42h3r-1.0.4.dist-info/LICENSE
ccheck_2l42h3r-1.0.4.dist-info/METADATA
ccheck_2l42h3r-1.0.4.dist-info/WHEEL
ccheck_2l42h3r-1.0.4.dist-info/top_level.txt
ccheck_2l42h3r-1.0.4.dist-info/RECORD
