Metadata-Version: 2.1
Name: ccheck-2l42h3r
Version: 1.0.4
Summary: A small C language exercise generator and checker
Home-page: https://github.com/2l42h3r/c-check
Author: Stanisław Uss
Author-email: uss.stanislaw@protonmail.com
Project-URL: Bug Tracker, https://github.com/2l42h3r/c-check/issues
Classifier: Programming Language :: Python :: 3
Classifier: License :: OSI Approved :: MIT License
Classifier: Operating System :: OS Independent
Requires-Python: >=3.7
License-File: LICENSE
Requires-Dist: dependency-injector (==4.39.1)
